handtex/__init__.py
handtex/about_driver.py
handtex/config.py
handtex/constants.py
handtex/data_recorder.py
handtex/driver_mainwindow.py
handtex/error_dialog_driver.py
handtex/gui_utils.py
handtex/issue_reporter_driver.py
handtex/license_driver.py
handtex/log_parser.py
handtex/log_viewer.py
handtex/main.py
handtex/sketchpad.py
handtex/state_saver.py
handtex/structures.py
handtex/symbol_list.py
handtex/symbol_relations.py
handtex/utils.py
handtex/worker_thread.py
handtex/CustomQ/CComboBox.py
handtex/CustomQ/CListWidget.py
handtex/CustomQ/CRegexLineEdit.py
handtex/CustomQ/CScrollArea.py
handtex/CustomQ/__init__.py
handtex/data/NotoMono-Regular.ttf
handtex/data/__init__.py
handtex/data/symbols.tar.xz
handtex/data/color_themes/__init__.py
handtex/data/color_themes/breeze
handtex/data/color_themes/breeze-dark
handtex/data/custom_icons/__init__.py
handtex/data/custom_icons/heart.svg
handtex/data/custom_icons/image-missing.svg
handtex/data/custom_icons/logo.ico
handtex/data/custom_icons/logo.svg
handtex/data/custom_icons/dark/stroke12.svg
handtex/data/custom_icons/dark/stroke16.svg
handtex/data/custom_icons/dark/stroke2.svg
handtex/data/custom_icons/dark/stroke20.svg
handtex/data/custom_icons/dark/stroke4.svg
handtex/data/custom_icons/dark/stroke6.svg
handtex/data/custom_icons/dark/stroke8.svg
handtex/data/custom_icons/light/stroke1.svg
handtex/data/custom_icons/light/stroke12.svg
handtex/data/custom_icons/light/stroke16.svg
handtex/data/custom_icons/light/stroke2.svg
handtex/data/custom_icons/light/stroke20.svg
handtex/data/custom_icons/light/stroke4.svg
handtex/data/custom_icons/light/stroke6.svg
handtex/data/custom_icons/light/stroke8.svg
handtex/data/model/__init__.py
handtex/data/model/encodings.txt
handtex/data/model/handtex.safetensors
handtex/data/symbol_metadata/__init__.py
handtex/data/symbol_metadata/augmented_symbol_frequency.csv
handtex/data/symbol_metadata/inside.txt
handtex/data/symbol_metadata/negations.txt
handtex/data/symbol_metadata/similar_astro.txt
handtex-1.0.4.dist-info/licenses/LICENSE
handtex-1.0.4.dist-info/METADATA
handtex-1.0.4.dist-info/WHEEL
handtex-1.0.4.dist-info/entry_points.txt
handtex-1.0.4.dist-info/top_level.txt
handtex-1.0.4.dist-info/RECORD
