Metadata-Version: 2.4
Name: handtex
Version: 1.0.4
Summary: Handwritten LaTeX symbol classifier for the desktop
Home-page: https://github.com/VoxelCubes/Hand-TeX
Keywords: LaTeX,TeX,handwriting,detection,classification,symbol,OCR,GUI,desktop,Qt
Classifier: Programming Language :: Python :: 3.10
Classifier: Operating System :: POSIX :: Linux
Classifier: Operating System :: Microsoft :: Windows
Requires-Python: >=3.10
License-File: LICENSE
Requires-Dist: attrs
Requires-Dist: loguru
Requires-Dist: PySide6
Requires-Dist: xdg
Requires-Dist: psutil
Requires-Dist: numpy
Requires-Dist: rdp
Requires-Dist: torch
Requires-Dist: torchvision
Requires-Dist: natsort
Requires-Dist: safetensors
Requires-Dist: networkx
Requires-Dist: pillow
Dynamic: license-file
